_retracesoftware_utils_debug.cpython-311-i386-linux-gnu.so
_retracesoftware_utils_release.cpython-311-i386-linux-gnu.so
retracesoftware_utils-0.2.10.dist-info/WHEEL
retracesoftware_utils-0.2.10.dist-info/METADATA
retracesoftware_utils-0.2.10.dist-info/RECORD
retracesoftware/utils/__init__.py
