Metadata-Version: 2.1
Name: retracesoftware_utils
Version: 0.2.10
Keywords: functional,programming,c-extension,utilities,performance
Author-Email: Retrace Software <info@retracesoftware.com>
Maintainer-Email: Retrace Software <info@retracesoftware.com>
License: Apache-2.0
Classifier: Development Status :: 4 - Beta
Classifier: Intended Audience :: Developers
Classifier: License :: OSI Approved :: Apache Software License
Classifier: Operating System :: OS Independent
Classifier: Programming Language :: Python :: 3
Classifier: Programming Language :: Python :: 3.11
Classifier: Programming Language :: Python :: Implementation :: CPython
Classifier: Topic :: Software Development :: Libraries :: Python Modules
Requires-Dist: retracesoftware.functional~=0.3.5
